finatic_client_python-0.1.0.dist-info/METADATA
finatic_client_python-0.1.0.dist-info/WHEEL
finatic/client.py
finatic/exceptions.py
finatic/models.py
finatic/_core.pyi
finatic/_core.rs
finatic/__init__.py
finatic/_core.cp313-win_amd64.pyd
finatic_client_python-0.1.0.dist-info/RECORD
